gacf/__init__.py
gacf/correlator.cpython-37m-darwin.so
gacf/datastructure.cpython-37m-darwin.so
gacf/gacf.py
gacf-1.1.dist-info/LICENSE
gacf-1.1.dist-info/METADATA
gacf-1.1.dist-info/WHEEL
gacf-1.1.dist-info/top_level.txt
gacf-1.1.dist-info/RECORD
